foliant/preprocessors/includes.py
foliantcontrib_includes-1.1.20.dist-info/licenses/LICENSE
foliantcontrib_includes-1.1.20.dist-info/METADATA
foliantcontrib_includes-1.1.20.dist-info/WHEEL
foliantcontrib_includes-1.1.20.dist-info/top_level.txt
foliantcontrib_includes-1.1.20.dist-info/RECORD
